ravendb/__init__.py
ravendb/changes/__init__.py
ravendb/changes/database_changes.py
ravendb/changes/observers.py
ravendb/changes/types.py
ravendb/data/__init__.py
ravendb/data/operation.py
ravendb/data/query.py
ravendb/documents/__init__.py
ravendb/documents/bulk_insert_operation.py
ravendb/documents/conventions.py
ravendb/documents/documents.py
ravendb/documents/time_series.py
ravendb/documents/ai/__init__.py
ravendb/documents/ai/ai_agent_parameters_builder.py
ravendb/documents/ai/ai_conversation.py
ravendb/documents/ai/ai_conversation_operations.py
ravendb/documents/ai/ai_conversation_result.py
ravendb/documents/ai/ai_operations.py
ravendb/documents/commands/__init__.py
ravendb/documents/commands/batches.py
ravendb/documents/commands/bulkinsert.py
ravendb/documents/commands/crud.py
ravendb/documents/commands/explain.py
ravendb/documents/commands/multi_get.py
ravendb/documents/commands/query.py
ravendb/documents/commands/results.py
ravendb/documents/commands/revisions.py
ravendb/documents/commands/stream.py
ravendb/documents/commands/subscriptions.py
ravendb/documents/identity/__init__.py
ravendb/documents/identity/hilo.py
ravendb/documents/indexes/__init__.py
ravendb/documents/indexes/abstract_index_creation_tasks.py
ravendb/documents/indexes/counters.py
ravendb/documents/indexes/definitions.py
ravendb/documents/indexes/index_creation.py
ravendb/documents/indexes/stats.py
ravendb/documents/indexes/time_series.py
ravendb/documents/indexes/analysis/__init__.py
ravendb/documents/indexes/analysis/definitions.py
ravendb/documents/indexes/spatial/__init__.py
ravendb/documents/indexes/spatial/configuration.py
ravendb/documents/indexes/vector/__init__.py
ravendb/documents/indexes/vector/embedding.py
ravendb/documents/indexes/vector/options.py
ravendb/documents/operations/__init__.py
ravendb/documents/operations/batch.py
ravendb/documents/operations/compact.py
ravendb/documents/operations/connection_strings.py
ravendb/documents/operations/counters.py
ravendb-7.1.2.post3.dist-info/METADATA
ravendb-7.1.2.post3.dist-info/WHEEL
ravendb-7.1.2.post3.dist-info/top_level.txt
ravendb-7.1.2.post3.dist-info/RECORD
