Metadata-Version: 2.4
Name: ravendb
Version: 7.1.2.post3
Summary: Python client for RavenDB NoSQL Database
Home-page: https://github.com/ravendb/ravendb-python-client
Author: RavenDB
Author-email: support@ravendb.net
License: MIT
Keywords: ravendb,nosql,databasepyravendb
Requires-Python: ~=3.9
Requires-Dist: requests~=2.32.0
Requires-Dist: requests-pkcs12>=1.13
Requires-Dist: pyOpenSSL>=22.0.0
Requires-Dist: ijson~=3.2.3
Requires-Dist: websocket-client>=0.46.0
Requires-Dist: inflect>=5.4.0
Dynamic: author
Dynamic: author-email
Dynamic: description
Dynamic: description-content-type
Dynamic: home-page
Dynamic: keywords
Dynamic: license
Dynamic: requires-dist
Dynamic: requires-python
Dynamic: summary
